<?xml version="1.0"?>

<!--  
   Copyright 2008 University of Rochester

   Licensed under the Apache License, Version 2.0 (the "License");
   you may not use this file except in compliance with the License.
   You may obtain a copy of the License at

       http://www.apache.org/licenses/LICENSE-2.0

   Unless required by applicable law or agreed to in writing, software
   distributed under the License is distributed on an "AS IS" BASIS,
   WITHOUT WARRANTIES OR CONDITIONS OF ANY KIND, either express or implied.
   See the License for the specific language governing permissions and
   limitations under the License.
-->   


<!DOCTYPE hibernate-mapping SYSTEM
			"http://hibernate.sourceforge.net/hibernate-mapping-3.0.dtd">
<!--
	Mapping for published date
	
	@author Sharmila Ranganathan
-->
<hibernate-mapping package="edu.ur.ir.item">
	<class name="PublishedDate" schema="ir_item" table="published_date"
		lazy="true">

		<!-- Common id property. -->
		<id name="id" type="long" column="published_date_id"
			unsaved-value="0" access="field">
			<generator class="sequence">
				<param name="sequence">ir_item.published_date_seq</param>
			</generator>
		</id>

		<!-- A versioned entity. -->
		<version name="version" column="version"
			access="org.hibernate.property.DirectPropertyAccessor" />
			
		<property name="day" column="day" type="int"
			access="field" />
			
		<property name="month" column="month" type="int"
			access="field" />

		<property name="year" column="year" type="int"
			access="field" />

		<property name="hours" column="hours" type="int"
			access="field" />

		<property name="minutes" column="minutes" type="int"
			access="field" />

		<property name="seconds" column="seconds" type="int"
			access="field" />

		<property name="fractionOfSecond" column="fraction_seconds" type="int"
			access="field" />
			
		<!--  Parent Item -->
		<many-to-one class="ExternalPublishedItem"
			name="externalPublishedItem" 
			column="external_published_item_id" 
			unique="true"
			insert="true"
			update="true" 
			access="field"/>   
		
		

	</class>
		
	<!--  Get a count of published dates in the system -->
	<query name="publishedDateCount">
	    select count(*) from PublishedDate
	</query>
	

</hibernate-mapping>